{
  "severity_counts": {
    "critical": 0,
    "high": 0,
    "medium": 0,
    "low": 0,
    "info": 0
  },
  "penalty_score": 1.0,
  "top_findings": [
    {
      "id": "R1",
      "kind": "requirement_implemented",
      "severity": "info",
      "title": "POST /books endpoint with validation",
      "evidence": "src/books/handler.clj:63, create-book function validates title and author, returns 201 Created on success",
      "suggestion": "\u2713 Complete"
    },
    {
      "id": "R2",
      "kind": "requirement_implemented",
      "severity": "info",
      "title": "GET /books with author filter support",
      "evidence": "src/books/handler.clj:64, list-books function handles optional author param; test/books/handler_test.clj:61-69 list-filter-test",
      "suggestion": "\u2713 Complete"
    },
    {
      "id": "R3",
      "kind": "requirement_implemented",
      "severity": "info",
      "title": "GET /books/{id} endpoint",
      "evidence": "src/books/handler.clj:65, get-book function with ID lookup; test/books/handler_test.clj:44-54 create-and-get-test",
      "suggestion": "\u2713 Complete"
    },
    {
      "id": "R4",
      "kind": "requirement_implemented",
      "severity": "info",
      "title": "PUT /books/{id} endpoint",
      "evidence": "src/books/handler.clj:66-67, update-book function; test/books/handler_test.clj:71-79 update-delete-test",
      "suggestion": "\u2713 Complete"
    },
    {
      "id": "R5",
      "kind": "requirement_implemented",
      "severity": "info",
      "title": "DELETE /books/{id} endpoint",
      "evidence": "src/books/handler.clj:68, delete-book function returns 204; test/books/handler_test.clj:71-79",
      "suggestion": "\u2713 Complete"
    }
  ],
  "requirement_coverage": 1.0,
  "model": "unknown",
  "evaluated_at": "2026-04-18T22:21:54.072857Z"
}